hmd_schema_loader/__init__.py
hmd_schema_loader/hmd_schema_loader.py
hmd_schema_loader-0.2.35.dist-info/METADATA
hmd_schema_loader-0.2.35.dist-info/WHEEL
hmd_schema_loader-0.2.35.dist-info/top_level.txt
hmd_schema_loader-0.2.35.dist-info/RECORD
