Metadata-Version: 2.1
Name: hmd-schema-loader
Version: 0.2.35
Summary: Python library for creating loaders for schema files.
Home-page: UNKNOWN
Author: Alex Burgoon
Author-email: alex.burgoon@hmdlabs.io
License: unlicensed
Platform: UNKNOWN
